taskshooter/__init__.py
taskshooter/config.py
taskshooter/scheduler.py
taskshooter/task.py
taskshooter/trigger.py
taskshooter/triggers.py
taskshooter-0.7.0.dist-info/WHEEL
taskshooter-0.7.0.dist-info/METADATA
taskshooter-0.7.0.dist-info/RECORD
