Metadata-Version: 2.1
Name: taskshooter
Version: 0.7.0
Summary: Library to schedule tasks with custom triggers.
Home-page: https://github.com/fedecalendino/taskshooter
License: MIT
Keywords: task,trigger,scheduler
Author: Fede Calendino
Author-email: fede@calendino.com
Requires-Python: >=3.10,<4.0
Classifier: Intended Audience :: Developers
Classifier: License :: OSI Approved :: MIT License
Classifier: Programming Language :: Python :: 3
Classifier: Programming Language :: Python :: 3.10
Classifier: Programming Language :: Python :: 3.11
Classifier: Programming Language :: Python :: 3.10
Classifier: Programming Language :: Python :: 3.11
Requires-Dist: pytz (>=2025.2,<2026.0)
Project-URL: Documentation, https://github.com/fedecalendino/taskshooter/blob/main/README.md
